pollination/irradiance/__init__.py
pollination/irradiance/_prepare_folder.py
pollination/irradiance/_raytracing.py
pollination/irradiance/entry.py
pollination_irradiance.express-0.0.10.dist-info/LICENSE
pollination_irradiance.express-0.0.10.dist-info/METADATA
pollination_irradiance.express-0.0.10.dist-info/WHEEL
pollination_irradiance.express-0.0.10.dist-info/top_level.txt
pollination_irradiance.express-0.0.10.dist-info/RECORD
