Metadata-Version: 2.1
Name: pollination-irradiance.express
Version: 0.0.10
Summary: Annual irradiance recipe for Pollination.
Home-page: https://github.com/pollination/irradiance
Author: pollination
Author-email: info@pollination.solutions
Maintainer: mostapha, ladybug-tools
Maintainer-email: mostapha@ladybug.tools, info@ladybug.tools
License: PolyForm Shield License 1.0.0, https://polyformproject.org/wp-content/uploads/2020/06/PolyForm-Shield-1.0.0.txt
Project-URL: icon, https://raw.githubusercontent.com/ladybug-tools/artwork/master/icons_components/honeybee/png/annualirrrecipe.png
Project-URL: docker, https://hub.docker.com/r/ladybugtools/honeybee-radiance
Keywords: honeybee,radiance,ladybug-tools,daylight,annual-irradiance
License-File: LICENSE
Requires-Dist: pollination-honeybee-radiance (>=0.22.47)
Requires-Dist: pollination-honeybee-radiance-postprocess (>=0.0.46)
Requires-Dist: pollination-alias (>=0.11.8)
Requires-Dist: pollination-path (>=0.3.2)
Provides-Extra: viz
Requires-Dist: pollination-honeybee-display (>=0.1.13) ; extra == 'viz'
